{
  "annotations": {
    "list": []
  },
  "description": "Live risk, recent executions, and intervention priority.",
  "editable": false,
  "fiscalYearStartMonth": 0,
  "graphTooltip": 1,
  "id": null,
  "links": [
    {
      "asDropdown": false,
      "icon": "external link",
      "includeVars": true,
      "keepTime": true,
      "tags": [],
      "targetBlank": false,
      "title": "Position & PnL Analytics",
      "tooltip": "",
      "type": "link",
      "url": "/d/bot-position-pnl"
    },
    {
      "asDropdown": false,
      "icon": "external link",
      "includeVars": true,
      "keepTime": true,
      "tags": [],
      "targetBlank": false,
      "title": "Telemetry & Provider Analytics",
      "tooltip": "",
      "type": "link",
      "url": "/d/bot-telemetry-provider"
    },
    {
      "asDropdown": false,
      "icon": "external link",
      "includeVars": true,
      "keepTime": true,
      "tags": [],
      "targetBlank": false,
      "title": "Executive Scorecard",
      "tooltip": "",
      "type": "link",
      "url": "/d/bot-executive-scorecard"
    }
  ],
  "panels": [
    {
      "id": 1,
      "title": "Open Positions",
      "type": "stat",
      "datasource": {
        "type": "postgres",
        "uid": "trading-bot-postgres"
      },
      "gridPos": {
        "h": 4,
        "w": 5,
        "x": 0,
        "y": 0
      },
      "targets": [
        {
          "datasource": {
            "type": "postgres",
            "uid": "trading-bot-postgres"
          },
          "editorMode": "code",
          "format": "table",
          "rawQuery": true,
          "rawSql": "SELECT COALESCE(open_positions, 0) AS value FROM v_runtime_live_status",
          "refId": "A"
        }
      ],
      "fieldConfig": {
        "defaults": {
          "unit": "none",
          "color": {
            "mode": "palette-classic"
          },
          "thresholds": {
            "mode": "absolute",
            "steps": [
              {
                "color": "green",
                "value": null
              },
              {
                "color": "red",
                "value": 0
              }
            ]
          }
        },
        "overrides": []
      },
      "options": {
        "colorMode": "value",
        "graphMode": "area",
        "justifyMode": "center",
        "orientation": "auto",
        "reduceOptions": {
          "calcs": [
            "lastNotNull"
          ],
          "fields": "",
          "values": false
        },
        "textMode": "auto"
      },
      "description": "Current open-position count from the live runtime snapshot."
    },
    {
      "id": 2,
      "title": "Exposure %",
      "type": "stat",
      "datasource": {
        "type": "postgres",
        "uid": "trading-bot-postgres"
      },
      "gridPos": {
        "h": 4,
        "w": 5,
        "x": 5,
        "y": 0
      },
      "targets": [
        {
          "datasource": {
            "type": "postgres",
            "uid": "trading-bot-postgres"
          },
          "editorMode": "code",
          "format": "table",
          "rawQuery": true,
          "rawSql": "SELECT COALESCE(((capital_usd - cash_usd)::numeric / NULLIF(capital_usd, 0)) * 100, 0) AS value FROM v_runtime_live_status",
          "refId": "A"
        }
      ],
      "fieldConfig": {
        "defaults": {
          "unit": "percent",
          "color": {
            "mode": "palette-classic"
          },
          "thresholds": {
            "mode": "absolute",
            "steps": [
              {
                "color": "green",
                "value": null
              },
              {
                "color": "red",
                "value": 0
              }
            ]
          }
        },
        "overrides": []
      },
      "options": {
        "colorMode": "value",
        "graphMode": "area",
        "justifyMode": "center",
        "orientation": "auto",
        "reduceOptions": {
          "calcs": [
            "lastNotNull"
          ],
          "fields": "",
          "values": false
        },
        "textMode": "auto"
      },
      "description": "Current deployed capital as a percentage of total capital."
    },
    {
      "id": 3,
      "title": "Cash On Hand",
      "type": "stat",
      "datasource": {
        "type": "postgres",
        "uid": "trading-bot-postgres"
      },
      "gridPos": {
        "h": 4,
        "w": 5,
        "x": 10,
        "y": 0
      },
      "targets": [
        {
          "datasource": {
            "type": "postgres",
            "uid": "trading-bot-postgres"
          },
          "editorMode": "code",
          "format": "table",
          "rawQuery": true,
          "rawSql": "SELECT COALESCE(cash_usd, 0) AS value FROM v_runtime_live_status",
          "refId": "A"
        }
      ],
      "fieldConfig": {
        "defaults": {
          "unit": "currencyUSD",
          "color": {
            "mode": "palette-classic"
          },
          "thresholds": {
            "mode": "absolute",
            "steps": [
              {
                "color": "green",
                "value": null
              },
              {
                "color": "red",
                "value": 0
              }
            ]
          }
        },
        "overrides": []
      },
      "options": {
        "colorMode": "value",
        "graphMode": "area",
        "justifyMode": "center",
        "orientation": "auto",
        "reduceOptions": {
          "calcs": [
            "lastNotNull"
          ],
          "fields": "",
          "values": false
        },
        "textMode": "auto"
      },
      "description": "Current available cash in the trading runtime."
    },
    {
      "id": 4,
      "title": "Recent Fills",
      "type": "stat",
      "datasource": {
        "type": "postgres",
        "uid": "trading-bot-postgres"
      },
      "gridPos": {
        "h": 4,
        "w": 5,
        "x": 15,
        "y": 0
      },
      "targets": [
        {
          "datasource": {
            "type": "postgres",
            "uid": "trading-bot-postgres"
          },
          "editorMode": "code",
          "format": "table",
          "rawQuery": true,
          "rawSql": "SELECT COALESCE(recent_fills, 0) AS value FROM v_runtime_live_status",
          "refId": "A"
        }
      ],
      "fieldConfig": {
        "defaults": {
          "unit": "none",
          "color": {
            "mode": "palette-classic"
          },
          "thresholds": {
            "mode": "absolute",
            "steps": [
              {
                "color": "green",
                "value": null
              },
              {
                "color": "red",
                "value": 0
              }
            ]
          }
        },
        "overrides": []
      },
      "options": {
        "colorMode": "value",
        "graphMode": "area",
        "justifyMode": "center",
        "orientation": "auto",
        "reduceOptions": {
          "calcs": [
            "lastNotNull"
          ],
          "fields": "",
          "values": false
        },
        "textMode": "auto"
      },
      "description": "Recently landed fills in the current live-monitor window."
    },
    {
      "id": 5,
      "title": "Stale Positions",
      "type": "stat",
      "datasource": {
        "type": "postgres",
        "uid": "trading-bot-postgres"
      },
      "gridPos": {
        "h": 4,
        "w": 4,
        "x": 20,
        "y": 0
      },
      "targets": [
        {
          "datasource": {
            "type": "postgres",
            "uid": "trading-bot-postgres"
          },
          "editorMode": "code",
          "format": "table",
          "rawQuery": true,
          "rawSql": "SELECT COALESCE(stale_positions, 0) AS value FROM v_runtime_live_status",
          "refId": "A"
        }
      ],
      "fieldConfig": {
        "defaults": {
          "unit": "none",
          "color": {
            "mode": "palette-classic"
          },
          "thresholds": {
            "mode": "absolute",
            "steps": [
              {
                "color": "green",
                "value": null
              },
              {
                "color": "red",
                "value": 0
              }
            ]
          }
        },
        "overrides": []
      },
      "options": {
        "colorMode": "value",
        "graphMode": "area",
        "justifyMode": "center",
        "orientation": "auto",
        "reduceOptions": {
          "calcs": [
            "lastNotNull"
          ],
          "fields": "",
          "values": false
        },
        "textMode": "auto"
      },
      "description": "Open positions missing fresh supporting evidence and likely needing intervention."
    },
    {
      "id": 6,
      "title": "Open Position Monitor",
      "type": "table",
      "datasource": {
        "type": "postgres",
        "uid": "trading-bot-postgres"
      },
      "gridPos": {
        "h": 10,
        "w": 16,
        "x": 0,
        "y": 4
      },
      "targets": [
        {
          "datasource": {
            "type": "postgres",
            "uid": "trading-bot-postgres"
          },
          "editorMode": "code",
          "format": "table",
          "rawQuery": true,
          "rawSql": "SELECT position_id, mint, symbol, source, exit_profile, tp_stage, live_price_usd, stop_distance_pct, return_pct, stale_minutes, intervention_priority, intervention_band, liquidity_usd, volume_5m_usd, buy_sell_ratio FROM v_open_position_monitor WHERE COALESCE(source::text, '') ~* '^(${source:regex})$' AND COALESCE(intervention_band::text, '') ~* '^(${interventionBand:regex})$' AND ('${mint}' = '' OR COALESCE(mint::text, '') ILIKE '%' || '${mint}' || '%') AND ('${symbol}' = '' OR COALESCE(symbol::text, '') ILIKE '%' || '${symbol}' || '%') AND ('${positionId}' = '' OR COALESCE(position_id::text, '') ILIKE '%' || '${positionId}' || '%') ORDER BY intervention_priority DESC, stale_minutes DESC",
          "refId": "A"
        }
      ],
      "fieldConfig": {
        "defaults": {},
        "overrides": []
      },
      "options": {
        "cellHeight": "sm",
        "footer": {
          "enablePagination": false,
          "reducer": [],
          "show": false
        },
        "showHeader": true
      },
      "description": "Priority-ranked open-book table for intervention-first monitoring."
    },
    {
      "id": 7,
      "title": "Lane Health",
      "type": "table",
      "datasource": {
        "type": "postgres",
        "uid": "trading-bot-postgres"
      },
      "gridPos": {
        "h": 10,
        "w": 8,
        "x": 16,
        "y": 4
      },
      "targets": [
        {
          "datasource": {
            "type": "postgres",
            "uid": "trading-bot-postgres"
          },
          "editorMode": "code",
          "format": "table",
          "rawQuery": true,
          "rawSql": "SELECT lane, status, detail, trade_mode, pause_reason, last_run_at, age_minutes, stale_after_minutes FROM v_runtime_lane_health ORDER BY lane",
          "refId": "A"
        }
      ],
      "fieldConfig": {
        "defaults": {},
        "overrides": []
      },
      "options": {
        "cellHeight": "sm",
        "footer": {
          "enablePagination": false,
          "reducer": [],
          "show": false
        },
        "showHeader": true
      },
      "description": "Current lane staleness and pause context from the runtime health contract."
    },
    {
      "id": 8,
      "title": "Recent Fill Activity",
      "type": "timeseries",
      "datasource": {
        "type": "postgres",
        "uid": "trading-bot-postgres"
      },
      "gridPos": {
        "h": 8,
        "w": 12,
        "x": 0,
        "y": 14
      },
      "targets": [
        {
          "datasource": {
            "type": "postgres",
            "uid": "trading-bot-postgres"
          },
          "editorMode": "code",
          "format": "time_series",
          "rawQuery": true,
          "rawSql": "SELECT created_at AS \"time\", side AS metric, amount_usd AS value FROM v_recent_fill_activity WHERE created_at >= $__timeFrom() AND created_at <= $__timeTo() AND COALESCE(source::text, '') ~* '^(${source:regex})$' AND ('${mint}' = '' OR COALESCE(mint::text, '') ILIKE '%' || '${mint}' || '%') AND ('${symbol}' = '' OR COALESCE(symbol::text, '') ILIKE '%' || '${symbol}' || '%') AND ('${positionId}' = '' OR COALESCE(position_id::text, '') ILIKE '%' || '${positionId}' || '%') ORDER BY 1, 2",
          "refId": "A"
        }
      ],
      "fieldConfig": {
        "defaults": {
          "unit": "currencyUSD",
          "color": {
            "mode": "palette-classic"
          },
          "custom": {
            "axisBorderShow": false,
            "axisCenteredZero": false,
            "axisColorMode": "text",
            "axisLabel": "",
            "axisPlacement": "auto",
            "barAlignment": 0,
            "drawStyle": "line",
            "fillOpacity": 10,
            "gradientMode": "none",
            "hideFrom": {
              "legend": false,
              "tooltip": false,
              "viz": false
            },
            "lineInterpolation": "linear",
            "lineWidth": 2,
            "pointSize": 4,
            "scaleDistribution": {
              "type": "linear"
            },
            "showPoints": "never",
            "spanNulls": false,
            "stacking": {
              "group": "A",
              "mode": "none"
            },
            "thresholdsStyle": {
              "mode": "off"
            }
          }
        },
        "overrides": []
      },
      "options": {
        "legend": {
          "displayMode": "list",
          "placement": "bottom",
          "showLegend": true
        },
        "tooltip": {
          "mode": "multi",
          "sort": "desc"
        }
      },
      "description": "Recent notional by fill side for the selected scope."
    },
    {
      "id": 9,
      "title": "Recent Fill Trail",
      "type": "table",
      "datasource": {
        "type": "postgres",
        "uid": "trading-bot-postgres"
      },
      "gridPos": {
        "h": 8,
        "w": 12,
        "x": 12,
        "y": 14
      },
      "targets": [
        {
          "datasource": {
            "type": "postgres",
            "uid": "trading-bot-postgres"
          },
          "editorMode": "code",
          "format": "table",
          "rawQuery": true,
          "rawSql": "SELECT created_at, side, position_id, mint, symbol, source, exit_profile, price_usd, amount_usd, pnl_usd, tx_signature FROM v_recent_fill_activity WHERE created_at >= $__timeFrom() AND created_at <= $__timeTo() AND COALESCE(source::text, '') ~* '^(${source:regex})$' AND ('${mint}' = '' OR COALESCE(mint::text, '') ILIKE '%' || '${mint}' || '%') AND ('${symbol}' = '' OR COALESCE(symbol::text, '') ILIKE '%' || '${symbol}' || '%') AND ('${positionId}' = '' OR COALESCE(position_id::text, '') ILIKE '%' || '${positionId}' || '%') ORDER BY created_at DESC LIMIT 100",
          "refId": "A"
        }
      ],
      "fieldConfig": {
        "defaults": {},
        "overrides": []
      },
      "options": {
        "cellHeight": "sm",
        "footer": {
          "enablePagination": false,
          "reducer": [],
          "show": false
        },
        "showHeader": true
      },
      "description": "Recent execution trail for the currently selected book slice."
    }
  ],
  "refresh": "30s",
  "schemaVersion": 41,
  "style": "dark",
  "tags": [
    "bot-trading",
    "operations",
    "live"
  ],
  "templating": {
    "list": [
      {
        "allValue": ".*",
        "current": {
          "selected": false,
          "text": "All",
          "value": ".*"
        },
        "datasource": {
          "type": "postgres",
          "uid": "trading-bot-postgres"
        },
        "definition": "SELECT DISTINCT source AS __text, source AS __value FROM v_open_position_monitor ORDER BY 1",
        "hide": 0,
        "includeAll": true,
        "label": "Source",
        "multi": true,
        "name": "source",
        "options": [],
        "query": "SELECT DISTINCT source AS __text, source AS __value FROM v_open_position_monitor ORDER BY 1",
        "refresh": 2,
        "sort": 1,
        "type": "query"
      },
      {
        "allValue": ".*",
        "current": {
          "selected": false,
          "text": "All",
          "value": ".*"
        },
        "datasource": {
          "type": "postgres",
          "uid": "trading-bot-postgres"
        },
        "definition": "SELECT DISTINCT intervention_band AS __text, intervention_band AS __value FROM v_open_position_monitor ORDER BY 1",
        "hide": 0,
        "includeAll": true,
        "label": "Intervention Band",
        "multi": true,
        "name": "interventionBand",
        "options": [],
        "query": "SELECT DISTINCT intervention_band AS __text, intervention_band AS __value FROM v_open_position_monitor ORDER BY 1",
        "refresh": 2,
        "sort": 1,
        "type": "query"
      },
      {
        "current": {
          "selected": false,
          "text": "",
          "value": ""
        },
        "hide": 0,
        "label": "Mint",
        "name": "mint",
        "options": [],
        "query": "",
        "skipUrlSync": false,
        "type": "textbox"
      },
      {
        "current": {
          "selected": false,
          "text": "",
          "value": ""
        },
        "hide": 0,
        "label": "Symbol",
        "name": "symbol",
        "options": [],
        "query": "",
        "skipUrlSync": false,
        "type": "textbox"
      },
      {
        "current": {
          "selected": false,
          "text": "",
          "value": ""
        },
        "hide": 0,
        "label": "Position ID",
        "name": "positionId",
        "options": [],
        "query": "",
        "skipUrlSync": false,
        "type": "textbox"
      }
    ]
  },
  "time": {
    "from": "now-6h",
    "to": "now"
  },
  "timepicker": {},
  "timezone": "browser",
  "title": "Live Trade Monitor",
  "uid": "bot-live-trade-monitor",
  "version": 1,
  "weekStart": "monday"
}
